{
  "serverIp": "8b8t.me",
  "lastUpdated": "23:20:33 25/1/2026",
  "totalKits": 40,
  "todayKits": 40,
  "onlineCount": 33,
  "peakPlayers": 38,
  "tps": "4.0",
  "ping": 269,
  "topUsers": [
    {
      "name": "LyoxYT",
      "count": 7
    },
    {
      "name": "ItsMeMario_XD",
      "count": 6
    },
    {
      "name": "Ayden322",
      "count": 5
    },
    {
      "name": "doyoda1292",
      "count": 4
    },
    {
      "name": ".Maddie8171111",
      "count": 4
    },
    {
      "name": "Murad2002",
      "count": 4
    },
    {
      "name": "CHRastyyy",
      "count": 3
    },
    {
      "name": "VientMC",
      "count": 3
    },
    {
      "name": "ReljKo7",
      "count": 2
    },
    {
      "name": "botchaosonix666",
      "count": 2
    }
  ],
  "topKits": [
    {
      "name": "dupe",
      "count": 12
    },
    {
      "name": "pvp",
      "count": 11
    },
    {
      "name": "elytra",
      "count": 6
    },
    {
      "name": "survival",
      "count": 4
    },
    {
      "name": "stash",
      "count": 3
    }
  ],
  "chatLog": [
    "[16:19] <Nighten2> plz dont raid my base :sob: ",
    "[16:19] liviaaaaaaa Whispers: !kit survival",
    "[16:19] [8b8t] >> Teleporting to home 0...",
    "[16:19] [8b8t] >> Teleporting to home 1...",
    "[16:19] To liviaaaaaaa: Your kit (survival) will be delivered in 30 seconds! Dont forget to join dsc.gg/hienbot",
    "[16:19] <WildCreativity> 0_heinbot so dub he said 'whats up _heinbot? ",
    "[16:19] To liviaaaaaaa: Please chat \"/tpayes 0_HienBot\" within 35 seconds! Join dsc.gg/hienbot for updates.",
    "[16:19] [BOT] <0_HienBot> >To change your password use the command /changepass <current password> <new password> ",
    "[16:19] [8b8t] >> Request sent to liviaaaaaaa",
    "[16:19] [8b8t] >> Teleporting...",
    "[16:19] [8b8t] >> You have killed yourself!",
    "[16:19] [8b8t] >> Donate to support 8b8t at https://shop.8b8t.me",
    "[16:19] <dylans117877601> @xx_COCACOLA_XX ",
    "[16:19] [8b8t] >> Teleporting to home 0...",
    "[16:19] [8b8t] >> Teleporting to home 4...",
    "[16:19] To dylans117877601: Kit \"xx_cocacola_xx\" not found! Giving you (food) instead! dsc.gg/hienbot",
    "[16:19] To dylans117877601: Please chat \"/tpayes 0_HienBot\" within 35 seconds! Join dsc.gg/hienbot for updates.",
    "[16:19] [8b8t] >> Request sent to dylans117877601",
    "[16:19] [BOT] <0_HienBot> >Hmmmmmmmmm ",
    "[16:19] <.wietyy> :list ",
    "[16:19] To .wietyy: Please wait a moment. Dont forget to join HienBot Group dsc.gg/hienbot",
    "[16:20] <WildCreativity> i almost read @xx ",
    "[16:20] [8b8t] >> Teleporting...",
    "[16:20] <botchaosonix666> cool ",
    "[16:20] [BOT] <0_HienBot> >Donate to maintain this great server donate▪8b8t▪me ",
    "[16:20] [8b8t] >> You have killed yourself!",
    "[16:20] <Nighten2> ty ",
    "[16:20] <WildCreativity> i almost read @xx_colacola_xxd ",
    "[16:20] <Nighten2> wait ",
    "[16:20] <Nighten2> u got trims "
  ],
  "userStats": {
    "Hien2309": 1,
    "doyoda1292": 4,
    ".monolithpm": 1,
    "ItsMeMario_XD": 6,
    "LyoxYT": 7,
    "ReljKo7": 2,
    "botchaosonix666": 2,
    "Ayden322": 5,
    ".Maddie8171111": 4,
    "CHRastyyy": 3,
    "VientMC": 3,
    "liviaaaaaaa": 2,
    ".wietyy": 2,
    "Murad2002": 4,
    "AdustCloud3179": 2,
    "dylans117877601": 1
  },
  "kitStats": {
    "stash": 3,
    "pvp": 11,
    "build": 1,
    "dupe": 12,
    "survival": 4,
    "elytra": 6,
    "exp": 1,
    "shulker": 2,
    "redstone": 1,
    "lightsources": 1,
    "gap": 1,
    "wood": 3,
    "gterracotta": 1,
    "armortrims": 1,
    "food": 1
  }
}