{
  "serverIp": "8b8t.me",
  "lastUpdated": "10:12:10 9/12/2025",
  "totalKits": 61348,
  "todayKits": 59,
  "onlineCount": 21,
  "peakPlayers": 44,
  "tps": "15.0",
  "ping": 232,
  "topUsers": [
    {
      "name": "Scotty_01_",
      "count": 91
    },
    {
      "name": "blepmonster",
      "count": 62
    },
    {
      "name": "m9anx",
      "count": 56
    },
    {
      "name": "3lch1ch4",
      "count": 48
    },
    {
      "name": "RiseCPvP",
      "count": 35
    },
    {
      "name": "WerxyLo",
      "count": 32
    },
    {
      "name": "spinchase",
      "count": 32
    },
    {
      "name": "MintKoala997563",
      "count": 29
    },
    {
      "name": "Kraxxyz",
      "count": 27
    },
    {
      "name": "zChrisw",
      "count": 27
    }
  ],
  "topKits": [
    {
      "name": "pvp",
      "count": 484
    },
    {
      "name": "survival",
      "count": 383
    },
    {
      "name": "tools",
      "count": 115
    },
    {
      "name": "dupe",
      "count": 103
    },
    {
      "name": "build",
      "count": 78
    }
  ],
  "chatLog": [
    "[10:05] [8b8t] >> Visit https://votefor.8b8t.me and vote to receive 2 additional render distance, 5 extra homes and access to the donkey dupe for free",
    "[10:05] LegitScene has made the advancement [Who is Cutting Onions?]",
    "[10:05] [BOT] <0_HienBot> Want to see your ping? Chat !ğ’‘ğ’Šğ’ğ’ˆ ",
    "[10:05] SH4D8W0 was pwned by Dinauxili wielding [their hand]",
    "[10:06] kakarotoVR_YT has made the advancement [Acquire Hardware]",
    "[10:06] [BOT] <0_HienBot> Give us feedback and ideas for kits in HienBot Group: dsc,gg/hienbot ",
    "[10:06] kakarotoVR_YT has made the advancement [Isn't It Iron Pick]",
    "[10:06] <.P1nkNeo> puro pendejo conectado ",
    "[10:06] [BOT] <0_HienBot> For each invitation in HienBot Group, you will receive 10 kits: dsc,gg/hienbot ",
    "[10:06] [8b8t] >> Visit https://votefor.8b8t.me and vote to receive 2 additional render distance, 5 extra homes and access to the donkey dupe for free",
    "[10:06] LegitScene got the wither disease",
    "[10:07] [BOT] <0_HienBot> ğ™’ğ™–ğ™£ğ™© ğ™ ğ™ğ™© ?? ğ˜¾ğ™ğ™–ğ™© !ğ™ ğ™ğ™© ",
    "[10:07] kakarotoVR_YT has made the advancement [Diamonds!]",
    "[10:07] [BOT] <0_HienBot> August 15 2025, the Avolution team boxed the Nether spawn with 3 obsidian walls ",
    "[10:07] LegitScene got the wither disease",
    "[10:08] [BOT] <0_HienBot> Maybe you don't know 0_HienBot doesn't have coordlogger you can see here tinyurlâ–ªcom/Hien2309ontopp ",
    "[10:08] [8b8t] >> Join the official announcement discord server at https://discord.8b8t.me",
    "[10:08] [BOT] <0_HienBot> Hmmmmmmmmm ",
    "[10:09] [BOT] <0_HienBot> Hmmmmmmmmm ",
    "[10:09] [BOT] <0_HienBot> Want to see the server's tps? Chat !ğ’•ğ’‘ğ’” ",
    "[10:09] [8b8t] >> Visit https://votefor.8b8t.me and vote to receive 2 additional render distance, 5 extra homes and access to the donkey dupe for free",
    "[10:10] <jhacks2> dupe ",
    "[10:10] [BOT] <0_HienBot> ğ‘»ğ’“ğ’š !ğ’Œğ’Šğ’• ğ’”ğ’•ğ’‚ğ’”ğ’‰ ",
    "[10:10] [BOT] <0_HienBot> Want to see whose ping is the best? Chat !ğ’ƒğ’†ğ’”ğ’•ğ’‘ğ’Šğ’ğ’ˆ ",
    "[10:11] [BOT] <0_HienBot> Try /nc to change your name color! ",
    "[10:11] UsuX has made the advancement [Diamonds!]",
    "[10:11] [8b8t] >> Join the official matrix chat at https://matrix.8b8t.me",
    "[10:11] UsuX has made the advancement [Acquire Hardware]",
    "[10:11] [BOT] <0_HienBot> Do !discord ",
    "[10:11] [8b8t] >> Please wait at least 2 seconds between chat messages"
  ],
  "userStats": {
    "Alecraft8": 17,
    "Victua7397": 7,
    "FlygDaa": 5,
    "WebSuperOp": 10,
    "RyloMC": 6,
    "pibble": 2,
    "bigbear": 13,
    "luccah10": 19,
    ".ThunderDrgn2845": 5,
    "2young2care": 1,
    "cuenta1213213": 3,
    "paidpopbob": 1,
    ".MISPOK9194": 13,
    "Hien2309": 15,
    "m9anx": 56,
    "xsNerox": 2,
    "RiseCPvP": 35,
    "dylan20392334": 3,
    ".Fofolowwy": 1,
    "visfocri": 9,
    "Krisspyy": 1,
    "elpp4073": 15,
    "chetosconqueso": 24,
    ".Mathius_Z": 1,
    "TylerDurden098": 5,
    "Dreamwonbtw100k": 14,
    "MaxFK166": 1,
    "Seasmd": 1,
    "Season12312": 1,
    "nicealts_ZURmw": 6,
    ".Pig7903": 2,
    "Leo_Arcade": 13,
    "Kraxxyz": 27,
    "DeoDevil": 20,
    "sitckmanvr1k": 3,
    ".Sadan6668": 1,
    "YusufChain31": 4,
    "WerxyLo": 32,
    "ayan_legion": 7,
    "Zetmin": 2,
    "Lukass_012": 20,
    "Doggy_wolf777": 19,
    "Gaelito28YT": 1,
    "aaaaaau": 4,
    "GoodNightaikoo": 6,
    "AlexOtero2012": 23,
    "Live_Leak": 2,
    "Skullziy": 3,
    "ReljKo7": 3,
    "UNHORIZON": 2,
    "KUTYA123676": 1,
    "The_Bot_father": 8,
    "Vladmir25": 4,
    "minerperson8201": 11,
    "keevin": 2,
    "zxcvutn": 3,
    "Savoir_40": 3,
    "Mxco_ball": 6,
    "Serbere_DK": 1,
    "creator79367": 3,
    "baccu_gamer_69": 1,
    "Bakivn_bot": 4,
    "c4tk": 5,
    "uigg": 2,
    "denise334": 7,
    "oRiolon1": 1,
    "Emirbaba72926": 1,
    "HCM100": 1,
    "person1100nc": 2,
    "Sniptoes": 1,
    "Pia01_Vn": 8,
    "Poptobaco": 1,
    "milomilom": 7,
    "GreetedWinter81": 7,
    "alisium44": 7,
    "Raiyan": 3,
    "blepmonster": 62,
    "WembuMC": 2,
    "Lins_42": 1,
    "Scotty_01_": 91,
    "ponfhj": 3,
    "youssef0useer": 5,
    "KinGvOnDieD": 10,
    "Loxiww": 3,
    "Exploterxyz": 12,
    "Ludrian": 1,
    "Minhprovip124": 6,
    "MintKoala997563": 29,
    "axel1241": 1,
    "Murad2002": 5,
    "ANONIMNO7627": 1,
    "VOLTAIKKKKK": 3,
    "Shirx_x": 8,
    "Ditoisbest": 2,
    "lxmz_": 1,
    "el_diddy123": 1,
    "ALSIO1243": 1,
    "RedSadBu": 14,
    "Lun4tic_": 1,
    "SiegeF16": 4,
    "mini_lake": 4,
    "gmares9919": 10,
    "likkalikkapoo": 5,
    "AtomicMaterials": 3,
    "maskurot": 7,
    "GaBaus": 3,
    "ayv3ee": 9,
    "Xoelsouto": 2,
    "3DProphet": 1,
    ".Uqe1": 22,
    "parhamzarea": 21,
    "PorotoCosmico": 1,
    "Josemhu12": 8,
    "d3m0n1010": 2,
    "AbdullahRihiczs": 1,
    "spinchase": 32,
    "HolaBroTasBien": 2,
    "3lch1ch4": 48,
    "neyouu": 1,
    "jokavavaii": 1,
    "lajosthehun": 2,
    "sekoppp": 1,
    "ronnythebeast": 1,
    "verbinen": 1,
    ".Jr7117": 4,
    "Tokizumi": 2,
    "Felpizin_Br": 22,
    "oniwolday": 12,
    ".Bobbycull": 4,
    "gmplayer13": 1,
    "camilogod": 12,
    "hankdrass": 4,
    "hunter2054": 11,
    "TheFuentxs_": 1,
    "Kaoliy77": 1,
    "zChrisw": 27,
    "iamyou123": 2,
    "LonkPAPU": 16,
    "pepito5986378946": 14,
    "ZojiFujita": 13,
    "EliseoBana": 1,
    ".AoDxPrince": 15,
    ".unknownguy59093": 15,
    "Luminus542": 1,
    "i212": 1,
    ".ZvXoid2873": 2,
    ".Jkbra1127": 3,
    "NicXyz": 4,
    "LiluMC": 3,
    "magmitamp4": 3,
    "REdcoNs": 3,
    "lolsuperman": 2,
    "p3l1n_1945": 9,
    "ultopia": 1,
    "zelliy": 6,
    "lamohypy76": 22,
    "IlIlIlIIlIlIlIl": 1,
    "Sem_Patito": 1,
    "amostradinhoBW": 13,
    "_Danda_": 1,
    "Nahuatlatofl": 1,
    "Lxutyyyy": 1,
    "jorgc1011": 3,
    "Kaylaxa": 8,
    "JTgamingYT": 1,
    "Mr_KeyCk": 1,
    "tekupeadd": 1,
    "AbidWarrrior57": 2,
    "Gabrielcraft522": 1,
    "zdwag22": 2,
    ".Entity_3035099": 1,
    "Hugo552": 2,
    "BenKavun": 2,
    "lautarito888": 12,
    "anghelinho": 6,
    "dylnadupeprubea": 2,
    "Ender_PvP345": 10,
    "reckless7824": 5,
    ".Joseph1209491": 1,
    "imnothai": 1,
    "OanaVT": 2,
    "Mark7254": 3,
    "Kvarsian": 1,
    "hadi09": 1,
    "Red_Fragment_": 4,
    "angelpro38": 3,
    "elproplayerxddd": 3,
    "brunoxdxdurhj": 2,
    "Gorka772": 2,
    "dragonkit": 4,
    "JUSTLIKED": 7,
    "DaFuqBoomTaken": 1,
    "Xoladliac": 5,
    "TaupeKibbles354": 6,
    "Thomasfriend": 5,
    "SHIVARAJGAME": 3,
    "perezemiliano": 1,
    "chimtocackhung": 1,
    "Simson": 16,
    "Enero": 5,
    "IllegalBot": 2,
    "Flamy_wolf": 1,
    "mogalts_ortnG": 2,
    "Boywithmagic777": 1,
    "ferfixee": 6,
    "Red_FragmentBOT": 1,
    "Rubb_GJ": 1,
    "michcar2377": 1,
    "Rokoo511": 1,
    "FenixUIYT": 1,
    "GemitoY7166": 9,
    "SigismundAcre": 2,
    "michelzim525": 3,
    "PVPMODEON": 2,
    ".Ricsike30016": 1,
    "mmma1rquitosss": 11,
    "alastor_gamer89": 1,
    ".LEON50758": 3,
    "Saad2001": 2,
    "FABRICIO_CAPITO": 3,
    "TraceGuy": 1,
    "aleja170713": 3,
    "nahuelx_x": 8,
    "22AlanProGamer": 4,
    "mn_pvp": 2,
    "quiraxd": 1,
    "SHADOW_EO": 1,
    "Skibidi_Rizzler8": 1,
    "resge": 5,
    "osxtox": 1,
    "lorax": 1,
    ".Sami702MMPL": 2,
    "droppedbytupapa": 1,
    "Minecentrix": 3,
    "TyroneG": 8,
    "facmc": 2,
    "Alesecoo12345789": 6,
    "JULIANSPR": 17,
    "antonio7754": 1,
    "yopachat": 3,
    "postarget": 11,
    "proonoob": 1,
    ".Jacobkiller8803": 1,
    "abtin123456": 5,
    "BoroBhai": 3,
    "SanyYtPRO": 6,
    "djdjaroz": 8,
    "cuack3000": 16,
    "owrfino": 2,
    "0_HienBots.": 4,
    "Xavier059": 1,
    "nono_cat": 1,
    ".AoDxPrincess": 3,
    "yigogvasalia": 4,
    "poke2112xdwazaaa": 1,
    "Fxbian_THR": 1,
    "hxrus": 2,
    "sonephh": 1,
    "joacopr12": 1,
    "Zephyrion1": 1,
    "Lyreaxhh": 3,
    "LY7Andregz": 4,
    "Exility": 1,
    "Disar7w7": 2,
    "Gpkkkll": 7,
    "GPT_AI": 1,
    "yagoteaa": 4,
    "Davidsegov": 1,
    ".Maddie8171111": 2,
    "UsuX": 10,
    "sandor412": 1,
    "dudax": 4,
    "Malbacoo": 2,
    "Veurects": 1,
    "HawaiiSprite708": 2,
    "Gruemma28": 1
  },
  "kitStats": {
    "build": 78,
    "survival": 383,
    "pvp": 484,
    "dupe": 103,
    "tools": 115,
    "stash": 55,
    "raid": 59,
    "wood": 26,
    "exp": 54,
    "dye": 22,
    "wool": 8,
    "mineral": 40,
    "food": 27,
    "redstone": 34,
    "toolbox": 36,
    "quartz": 8,
    "shulker": 38,
    "terracotta": 4,
    "end": 15,
    "armortrims": 24,
    "highway": 23,
    "ocean": 4,
    "concrete": 22,
    "glass": 6,
    "gap": 3,
    "constructor": "function Object() { [native code] }1111",
    "flower": 1
  }
}