{
  "serverIp": "8b8t.me",
  "lastUpdated": "22:58:33 25/1/2026",
  "totalKits": 23,
  "todayKits": 23,
  "onlineCount": 36,
  "peakPlayers": 38,
  "tps": "3.0",
  "ping": 214,
  "topUsers": [
    {
      "name": "ItsMeMario_XD",
      "count": 6
    },
    {
      "name": "LyoxYT",
      "count": 6
    },
    {
      "name": "doyoda1292",
      "count": 4
    },
    {
      "name": ".Maddie8171111",
      "count": 3
    },
    {
      "name": "ReljKo7",
      "count": 2
    },
    {
      "name": "CHRastyyy",
      "count": 2
    },
    {
      "name": "Hien2309",
      "count": 1
    },
    {
      "name": ".monolithpm",
      "count": 1
    },
    {
      "name": "botchaosonix666",
      "count": 1
    },
    {
      "name": "Ayden322",
      "count": 1
    }
  ],
  "topKits": [
    {
      "name": "pvp",
      "count": 7
    },
    {
      "name": "elytra",
      "count": 6
    },
    {
      "name": "dupe",
      "count": 4
    },
    {
      "name": "stash",
      "count": 3
    },
    {
      "name": "build",
      "count": 1
    }
  ],
  "chatLog": [
    "[15:57] To VientMC: Please chat \"/tpayes 0_HienBot\" within 35 seconds! Join dsc.gg/hienbot for updates.",
    "[15:57] <.wietyy> !pvp ",
    "[15:57] [8b8t] >> Request sent to VientMC",
    "[15:57] <liviaaaaaaa> IM SO SORRY ",
    "[15:57] To .wietyy: Please wait a moment. Dont forget to join HienBot Group dsc.gg/hienbot",
    "[15:58] <CHRastyyy> someone tos me :ppp ",
    "[15:58] <Murad2002> !survival ",
    "[15:58] To Murad2002: Please wait a moment. Dont forget to join HienBot Group dsc.gg/hienbot",
    "[15:58] [8b8t] >> Teleporting...",
    "[15:58] <.Maddie8171111> its fine ",
    "[15:58] <CHRastyyy> tpa ",
    "[15:58] <CHRastyyy> * ",
    "[15:58] [8b8t] >> You have killed yourself!",
    "[15:58] <CHRastyyy> :o ",
    "[15:58] [BOT] <0_HienBot> >Do you want kit? Type *кιт ",
    "[15:58] [8b8t] >> Teleporting to home 0...",
    "[15:58] [8b8t] >> Teleporting to home 1...",
    "[15:58] To CHRastyyy: Kit \"o\" not found! Giving you (pvp) instead! dsc.gg/hienbot",
    "[15:58] To CHRastyyy: Please chat \"/tpayes 0_HienBot\" within 35 seconds! Join dsc.gg/hienbot for updates.",
    "[15:58] <Murad2002> !illegal ",
    "[15:58] To Murad2002: Please wait a moment. Dont forget to join HienBot Group dsc.gg/hienbot",
    "[15:58] [8b8t] >> Request sent to CHRastyyy",
    "[15:58] <Murad2002> !illegal ",
    "[15:58] To Murad2002: Please wait a moment. Dont forget to join HienBot Group dsc.gg/hienbot",
    "[15:58] <Murad2002> !illegal ",
    "[15:58] To Murad2002: Please wait a moment. Dont forget to join HienBot Group dsc.gg/hienbot",
    "[15:58] <Murad2002> !illegal ",
    "[15:58] To Murad2002: Please wait a moment. Dont forget to join HienBot Group dsc.gg/hienbot",
    "[15:58] [8b8t] >> Teleporting...",
    "[15:58] [8b8t] >> Join the official announcement discord server at https://discord.8b8t.me"
  ],
  "userStats": {
    "Hien2309": 1,
    "doyoda1292": 4,
    ".monolithpm": 1,
    "ItsMeMario_XD": 6,
    "LyoxYT": 6,
    "ReljKo7": 2,
    "botchaosonix666": 1,
    "Ayden322": 1,
    ".Maddie8171111": 3,
    "CHRastyyy": 2,
    "VientMC": 1
  },
  "kitStats": {
    "stash": 3,
    "pvp": 7,
    "build": 1,
    "dupe": 4,
    "survival": 1,
    "elytra": 6,
    "exp": 1,
    "shulker": 1,
    "redstone": 1,
    "lightsources": 1,
    "gap": 1,
    "wood": 1
  }
}