{
  "serverIp": "8b8t.me",
  "lastUpdated": "06:27:40 23/1/2026",
  "totalKits": 299,
  "todayKits": 299,
  "onlineCount": 24,
  "peakPlayers": 52,
  "tps": "3.0",
  "ping": 237,
  "topUsers": [
    {
      "name": "Super_jj9000",
      "count": 27
    },
    {
      "name": "dylans117877601",
      "count": 25
    },
    {
      "name": "alonsoalvape7",
      "count": 20
    },
    {
      "name": "fytasx",
      "count": 19
    },
    {
      "name": "miro09809808",
      "count": 19
    },
    {
      "name": "hamburguesa1234",
      "count": 18
    },
    {
      "name": "liviaaaaaaa",
      "count": 16
    },
    {
      "name": "Elrompepelotas",
      "count": 16
    },
    {
      "name": "elmataservers",
      "count": 15
    },
    {
      "name": "espinos",
      "count": 13
    }
  ],
  "topKits": [
    {
      "name": "pvp",
      "count": 59
    },
    {
      "name": "survival",
      "count": 45
    },
    {
      "name": "build",
      "count": 28
    },
    {
      "name": "elytra",
      "count": 27
    },
    {
      "name": "tools",
      "count": 25
    }
  ],
  "chatLog": [
    "[23:25] To jairoelpro: Please chat \"/tpayes 0_HienBot\" within 35 seconds! Join dsc.gg/hienbot for updates.",
    "[23:25] [8b8t] >> Request sent to jairoelpro",
    "[23:25] [BOT] <0_HienBot> >Do you want kit? Type !кιт ",
    "[23:25] [8b8t] >> Teleporting...",
    "[23:25] <fabric_XxX> !kit totems ",
    "[23:25] To fabric_XxX: Please wait a moment. Dont forget to join HienBot Group dsc.gg/hienbot",
    "[23:25] [8b8t] >> Visit https://votefor.8b8t.me and vote to receive 2 additional render distance, 5 extra homes and access to the donkey dupe for free",
    "[23:26] [XMAS2025] <elproplayerxddd> lito ",
    "[23:26] [Pro+] <Voltaikk> bueno ",
    "[23:26] <TulagrandBot> >Want kit? Try @kit ",
    "[23:26] <fabric_XxX> !kit survival ",
    "[23:26] [8b8t] >> You have killed yourself!",
    "[23:26] To fabric_XxX: Your kit (survival) will be delivered in 30 seconds! Dont forget to join dsc.gg/hienbot",
    "[23:26] [XMAS2025] <Tobias> culo ",
    "[23:26] [BOT] <0_HienBot> >In its beginnings 8b8t was actually called 0b0t ",
    "[23:26] [8b8t] >> Teleporting to home 0...",
    "[23:26] [8b8t] >> Teleporting to home 1...",
    "[23:26] To fabric_XxX: Please chat \"/tpayes 0_HienBot\" within 35 seconds! Join dsc.gg/hienbot for updates.",
    "[23:26] [8b8t] >> Request sent to fabric_XxX",
    "[23:26] [8b8t] >> Teleporting...",
    "[23:26] [8b8t] >> You have killed yourself!",
    "[23:26] [BOT] <0_HienBot> >Don't forget to vote for 8b8t at votefor▪8b8t▪me ",
    "[23:26] <ASXN> Alguien me puede ayudar?? ",
    "[23:27] <fabric_XxX> jairo team? ",
    "[23:27] [BOT] <0_HienBot> >Type !кιт  to get free kits ",
    "[23:27] <TulagrandBot> >Try @ping to get your ping ",
    "[23:27] <jairoelpro> dale espera que salgo del spawn ",
    "[23:27] <fabric_XxX> oke ",
    "[23:27] jairoelpro has made the advancement [Stone Age]",
    "[23:27] [8b8t] >> Join the official matrix chat at https://matrix.8b8t.me"
  ],
  "userStats": {
    "dylans117877601": 25,
    "Super_jj9000": 27,
    "obitokkkk": 1,
    "Anonymous204205": 1,
    "espinos": 13,
    "ICommitFraud_": 8,
    "Boolyymon": 4,
    "dragonkit": 1,
    "fytasx": 19,
    "ASXN": 12,
    "itz_ju4n": 2,
    "Gintars": 1,
    "ElTomatitoFresco": 3,
    "yra112": 1,
    "MrMidnight89": 1,
    ".BESTPLAYER7769": 1,
    "LaSoLaTu": 8,
    "verusxd22": 10,
    "angelcrawel": 2,
    "kaya_1": 7,
    "underd0sed": 1,
    "fabric_XxX": 12,
    "bautost2": 1,
    "miro09809808": 19,
    "AdixY": 1,
    "liviaaaaaaa": 16,
    "H_INMORTAL_M": 3,
    "ManePear_fannn": 2,
    "Arsago": 2,
    "alonsoalvape7": 20,
    "moonsystem4": 4,
    "Lnitox": 1,
    "HahaGirlYs": 2,
    "Lagas3331": 3,
    "GemitoY7166": 3,
    "Banan4ikins": 1,
    ".Alonso33curba": 3,
    "Akross17": 2,
    "hamburguesa1234": 18,
    "Error2211": 4,
    "botchaosonix": 7,
    "Elrompepelotas": 16,
    "alexito123456": 1,
    "ilovecatsvr57364": 3,
    "egzoegzo": 6,
    "deantheneek": 3,
    "Antonhysv": 3,
    ".Eden_01655": 1,
    "elproplayerxddd": 2,
    "nowayth1siused": 3,
    ".daualtibaqia": 2,
    "Soyvaquita": 1,
    "Khadu_fr": 10,
    "Gato77": 5,
    "euwyrlhi": 9,
    "KionYhamma": 3,
    "elmataservers": 15,
    ".LEON50758": 1,
    "Aeriak64HD": 2,
    "Xx_chamorro_xX": 7,
    "asciicat": 1,
    "NumbyFace": 4,
    "Exoshi": 1,
    ".Dark_Dbx24": 6,
    "Victorium_15": 1,
    "qwilzyDE4D": 1,
    "moonsystem6": 1,
    "Boumageos": 1,
    "jairoelpro": 2
  },
  "kitStats": {
    "build": 28,
    "raid": 16,
    "stash": 11,
    "wood": 11,
    "armortrims": 9,
    "glass": 5,
    "pvp": 59,
    "dye": 4,
    "dupe": 20,
    "gterracotta": 4,
    "redstone": 15,
    "mineral": 9,
    "exp": 12,
    "ocean": 3,
    "end": 8,
    "quartz": 3,
    "music": 2,
    "elytra": 27,
    "survival": 45,
    "tools": 25,
    "food": 8,
    "toolbox": 20,
    "concrete": 9,
    "highway": 7,
    "gap": 2,
    "wool": 7,
    "lightsources": 8,
    "shulker": 6
  }
}