{
  "serverIp": "8b8t.me",
  "lastUpdated": "14:34:35 8/12/2025",
  "totalKits": 60776,
  "todayKits": 3,
  "onlineCount": 13,
  "peakPlayers": 14,
  "tps": "20.0",
  "ping": 234,
  "topUsers": [
    {
      "name": "Scotty_01_",
      "count": 51
    },
    {
      "name": "m9anx",
      "count": 48
    },
    {
      "name": "blepmonster",
      "count": 38
    },
    {
      "name": "3lch1ch4",
      "count": 32
    },
    {
      "name": "WerxyLo",
      "count": 29
    },
    {
      "name": "RiseCPvP",
      "count": 27
    },
    {
      "name": "MintKoala997563",
      "count": 25
    },
    {
      "name": "Kraxxyz",
      "count": 22
    },
    {
      "name": "Felpizin_Br",
      "count": 22
    },
    {
      "name": "lamohypy76",
      "count": 20
    }
  ],
  "topKits": [
    {
      "name": "pvp",
      "count": 285
    },
    {
      "name": "survival",
      "count": 219
    },
    {
      "name": "tools",
      "count": 74
    },
    {
      "name": "dupe",
      "count": 70
    },
    {
      "name": "raid",
      "count": 43
    }
  ],
  "chatLog": [
    "[14:24] [BOT] <0_HienBot> Do !𝙠𝙞𝙩 ",
    "[14:24] [BOT] <0_HienBot> August 15 2025, the Avolution team boxed the Nether spawn with 3 obsidian walls ",
    "[14:24] [8b8t] >> Join the official announcement discord server at https://discord.8b8t.me",
    "[14:25] [BOT] <0_HienBot> Vietnam on top!! ",
    "[14:25] [BOT] <0_HienBot> Want to see the server's tps? Chat !𝒕𝒑𝒔 ",
    "[14:26] [BOT] <0_HienBot> 𝑻𝒓𝒚 !𝒌𝒊𝒕 𝒑𝒗𝒑 ",
    "[14:26] [8b8t] >> Visit https://votefor.8b8t.me and vote to receive 2 additional render distance, 5 extra homes and access to the donkey dupe for free",
    "[14:26] [BOT] <0_HienBot> Use /lobby to return to the lobby! ",
    "[14:27] [BOT] <0_HienBot> Use /kill to kill yourself! ",
    "[14:27] [BOT] <0_HienBot> Hello elproplayerxddd! ",
    "[14:27] [8b8t] >> Join the official announcement discord server at https://discord.8b8t.me",
    "[14:28] [BOT] <0_HienBot> Want to see whose ping is the best? Chat !𝒃𝒆𝒔𝒕𝒑𝒊𝒏𝒈 ",
    "[14:28] [BOT] <0_HienBot> Don't forget to vote for 8b8t at votefor▪8b8t▪me ",
    "[14:29] [BOT] <0_HienBot> Voting for the server will give you access to the /nc command and you can save up to 10 homes ",
    "[14:29] [8b8t] >> Visit https://votefor.8b8t.me and vote to receive 2 additional render distance, 5 extra homes and access to the donkey dupe for free",
    "[14:29] [BOT] <0_HienBot> Hmmmmmmmmm ",
    "[14:30] [BOT] <0_HienBot> Donate to maintain this great server donate▪8b8t▪me ",
    "[14:30] [BOT] <0_HienBot> 𝑻𝒓𝒚 !𝒌𝒊𝒕 𝒔𝒕𝒂𝒔𝒉 ",
    "[14:30] [8b8t] >> Donate to support 8b8t at https://shop.8b8t.me",
    "[14:31] [BOT] <0_HienBot> Hate those who destroy Hien2309's base ",
    "[14:31] [BOT] <0_HienBot> Save your password well, resetting it will cost you $5 dollars ",
    "[14:32] [BOT] <0_HienBot> Use /kill to kill yourself! ",
    "[14:32] [8b8t] >> Donate to support 8b8t at https://shop.8b8t.me",
    "[14:32] darsacc's mom said we have food at home",
    "[14:32] [BOT] <0_HienBot> Use !𝙠𝙞𝙩 to get kit ",
    "[14:32] <Skullziy> niggr ",
    "[14:33] [BOT] <0_HienBot> Voting for the server will give you access to the /nc command and you can save up to 10 homes ",
    "[14:33] [BOT] <0_HienBot> Use /lobby to return to the lobby! ",
    "[14:33] [8b8t] >> Visit https://votefor.8b8t.me and vote to receive 2 additional render distance, 5 extra homes and access to the donkey dupe for free",
    "[14:34] [BOT] <0_HienBot> August 15 2025, the Avolution team boxed the Nether spawn with 3 obsidian walls "
  ],
  "userStats": {
    "Alecraft8": 16,
    "Victua7397": 6,
    "FlygDaa": 5,
    "WebSuperOp": 10,
    "RyloMC": 6,
    "pibble": 2,
    "bigbear": 8,
    "luccah10": 16,
    ".ThunderDrgn2845": 5,
    "2young2care": 1,
    "cuenta1213213": 3,
    "paidpopbob": 1,
    ".MISPOK9194": 5,
    "Hien2309": 11,
    "m9anx": 48,
    "xsNerox": 2,
    "RiseCPvP": 27,
    "dylan20392334": 1,
    ".Fofolowwy": 1,
    "visfocri": 9,
    "Krisspyy": 1,
    "elpp4073": 2,
    "chetosconqueso": 2,
    ".Mathius_Z": 1,
    "TylerDurden098": 3,
    "Dreamwonbtw100k": 14,
    "MaxFK166": 1,
    "Seasmd": 1,
    "Season12312": 1,
    "nicealts_ZURmw": 6,
    ".Pig7903": 2,
    "Leo_Arcade": 13,
    "Kraxxyz": 22,
    "DeoDevil": 13,
    "sitckmanvr1k": 2,
    ".Sadan6668": 1,
    "YusufChain31": 4,
    "WerxyLo": 29,
    "ayan_legion": 5,
    "Zetmin": 2,
    "Lukass_012": 9,
    "Doggy_wolf777": 19,
    "Gaelito28YT": 1,
    "aaaaaau": 4,
    "GoodNightaikoo": 5,
    "AlexOtero2012": 12,
    "Live_Leak": 2,
    "Skullziy": 3,
    "ReljKo7": 2,
    "UNHORIZON": 1,
    "KUTYA123676": 1,
    "The_Bot_father": 7,
    "Vladmir25": 3,
    "minerperson8201": 3,
    "keevin": 2,
    "zxcvutn": 1,
    "Savoir_40": 3,
    "Mxco_ball": 6,
    "Serbere_DK": 1,
    "creator79367": 3,
    "baccu_gamer_69": 1,
    "Bakivn_bot": 4,
    "c4tk": 5,
    "uigg": 2,
    "denise334": 4,
    "oRiolon1": 1,
    "Emirbaba72926": 1,
    "HCM100": 1,
    "person1100nc": 2,
    "Sniptoes": 1,
    "Pia01_Vn": 8,
    "Poptobaco": 1,
    "milomilom": 5,
    "GreetedWinter81": 6,
    "alisium44": 6,
    "Raiyan": 1,
    "blepmonster": 38,
    "WembuMC": 2,
    "Lins_42": 1,
    "Scotty_01_": 51,
    "ponfhj": 3,
    "youssef0useer": 2,
    "KinGvOnDieD": 7,
    "Loxiww": 3,
    "Exploterxyz": 8,
    "Ludrian": 1,
    "Minhprovip124": 1,
    "MintKoala997563": 25,
    "axel1241": 1,
    "Murad2002": 5,
    "ANONIMNO7627": 1,
    "VOLTAIKKKKK": 2,
    "Shirx_x": 8,
    "Ditoisbest": 2,
    "lxmz_": 1,
    "el_diddy123": 1,
    "ALSIO1243": 1,
    "RedSadBu": 13,
    "Lun4tic_": 1,
    "SiegeF16": 4,
    "mini_lake": 4,
    "gmares9919": 10,
    "likkalikkapoo": 5,
    "AtomicMaterials": 3,
    "maskurot": 2,
    "GaBaus": 2,
    "ayv3ee": 6,
    "Xoelsouto": 2,
    "3DProphet": 1,
    ".Uqe1": 18,
    "parhamzarea": 6,
    "PorotoCosmico": 1,
    "Josemhu12": 5,
    "d3m0n1010": 2,
    "AbdullahRihiczs": 1,
    "spinchase": 8,
    "HolaBroTasBien": 2,
    "3lch1ch4": 32,
    "neyouu": 1,
    "jokavavaii": 1,
    "lajosthehun": 2,
    "sekoppp": 1,
    "ronnythebeast": 1,
    "verbinen": 1,
    ".Jr7117": 1,
    "Tokizumi": 2,
    "Felpizin_Br": 22,
    "oniwolday": 12,
    ".Bobbycull": 4,
    "gmplayer13": 1,
    "camilogod": 2,
    "hankdrass": 4,
    "hunter2054": 9,
    "TheFuentxs_": 1,
    "Kaoliy77": 1,
    "zChrisw": 13,
    "iamyou123": 2,
    "LonkPAPU": 16,
    "pepito5986378946": 14,
    "ZojiFujita": 13,
    "EliseoBana": 1,
    ".AoDxPrince": 5,
    ".unknownguy59093": 8,
    "Luminus542": 1,
    "i212": 1,
    ".ZvXoid2873": 2,
    ".Jkbra1127": 3,
    "NicXyz": 4,
    "LiluMC": 3,
    "magmitamp4": 3,
    "REdcoNs": 3,
    "lolsuperman": 2,
    "p3l1n_1945": 5,
    "ultopia": 1,
    "zelliy": 4,
    "lamohypy76": 20,
    "IlIlIlIIlIlIlIl": 1,
    "Sem_Patito": 1,
    "amostradinhoBW": 11,
    "_Danda_": 1,
    "Nahuatlatofl": 1,
    "Lxutyyyy": 1,
    "jorgc1011": 3,
    "Kaylaxa": 7,
    "JTgamingYT": 1,
    "Mr_KeyCk": 1,
    "tekupeadd": 1,
    "AbidWarrrior57": 1,
    "Gabrielcraft522": 1,
    "zdwag22": 2,
    ".Entity_3035099": 1,
    "Hugo552": 2,
    "BenKavun": 2,
    "lautarito888": 11,
    "anghelinho": 6,
    "dylnadupeprubea": 1,
    "Ender_PvP345": 5,
    "reckless7824": 4
  },
  "kitStats": {
    "build": 39,
    "survival": 219,
    "pvp": 285,
    "dupe": 70,
    "tools": 74,
    "stash": 30,
    "raid": 43,
    "wood": 17,
    "exp": 30,
    "dye": 14,
    "wool": 5,
    "mineral": 22,
    "food": 18,
    "redstone": 22,
    "toolbox": 21,
    "quartz": 7,
    "shulker": 16,
    "terracotta": 3,
    "end": 8,
    "armortrims": 13,
    "highway": 17,
    "ocean": 4,
    "concrete": 12,
    "glass": 2,
    "gap": 1
  }
}