{
  "serverIp": "8b8t.me",
  "lastUpdated": "12:11:57 7/12/2025",
  "totalKits": 60058,
  "todayKits": 9,
  "onlineCount": 30,
  "peakPlayers": 38,
  "tps": "14.0",
  "ping": 239,
  "topUsers": [
    {
      "name": "luccah10",
      "count": 10
    },
    {
      "name": "WebSuperOp",
      "count": 9
    },
    {
      "name": "m9anx",
      "count": 9
    },
    {
      "name": "RyloMC",
      "count": 6
    },
    {
      "name": "Hien2309",
      "count": 6
    },
    {
      "name": ".MISPOK9194",
      "count": 5
    },
    {
      "name": "RiseCPvP",
      "count": 4
    },
    {
      "name": "FlygDaa",
      "count": 3
    },
    {
      "name": "cuenta1213213",
      "count": 3
    },
    {
      "name": "pibble",
      "count": 2
    }
  ],
  "topKits": [
    {
      "name": "pvp",
      "count": 15
    },
    {
      "name": "tools",
      "count": 10
    },
    {
      "name": "survival",
      "count": 9
    },
    {
      "name": "wood",
      "count": 8
    },
    {
      "name": "build",
      "count": 5
    }
  ],
  "chatLog": [
    "[12:09] [8b8t] >> Please do not spam.",
    "[12:09] [8b8t] >> Visit https://votefor.8b8t.me and vote to receive 2 additional render distance, 5 extra homes and access to the donkey dupe for free",
    "[12:09] <.Pig7903> 2 kit ",
    "[12:09] <ABAB> nope ",
    "[12:09] <.Pig7903> 3 ",
    "[12:09] phong1992123 has made the advancement [Spooky Scary Skeleton]",
    "[12:09] <chetosconqueso> pvp¡¡¡ ",
    "[12:09] <.Pig7903> 5kits ",
    "[12:10] [BOT] <0_HienBot> Hi Fugitivies_24! ",
    "[12:10] <ABAB> im use hack bro ",
    "[12:10] <RiseCPvP> !kit tools ",
    "[12:10] [8b8t] >> Teleporting to home 0...",
    "[12:10] [8b8t] >> Teleporting to home 8...",
    "[12:10] To RiseCPvP: Your kit (tools) will be delivered in less than 30 seconds! Dont forget to join HienBot Group dsc.gg／HienBot",
    "[12:10] To RiseCPvP: Sorry! Yellow Shulker Box is out of stock. Giving you Light Blue Shulker Box instead!",
    "[12:10] [8b8t] >> Request sent to RiseCPvP",
    "[12:10] [8b8t] >> Teleporting...",
    "[12:10] [BOT] <0_HienBot> Hate those who destroy Hien2309's base ",
    "[12:10] 0_HienBot was destroyed by RiseCPvP",
    "[12:10] [8b8t] >> Home 2 was not found",
    "[12:10] [8b8t] >> The command /seed is not allowed",
    "[12:10] .Mathius_Z thought they could fly... they couldn't",
    "[12:10] [8b8t] >> The command /seed is not allowed",
    "[12:10] [8b8t] >> The command /seed is not allowed",
    "[12:10] <.Pig7903> U can hack or not but i dont hack ",
    "[12:11] [BOT] <0_HienBot> Give us feedback and ideas for kits in HienBot Group: dsc,gg/hienbot ",
    "[12:11] [8b8t] >> Join the official announcement discord server at https://discord.8b8t.me",
    "[12:11] chetosconqueso has reached the goal [Postmortal]",
    "[12:11] [BOT] <0_HienBot> Maybe you don't know 0_HienBot doesn't have coordlogger you can see here tinyurl▪com/Hien2309ontopp ",
    "[12:11] Hien2309 has completed the challenge [Smithing with Style]"
  ],
  "userStats": {
    "Alecraft8": 1,
    "Victua7397": 1,
    "FlygDaa": 3,
    "WebSuperOp": 9,
    "RyloMC": 6,
    "pibble": 2,
    "bigbear": 2,
    "luccah10": 10,
    ".ThunderDrgn2845": 2,
    "2young2care": 1,
    "cuenta1213213": 3,
    "paidpopbob": 1,
    ".MISPOK9194": 5,
    "Hien2309": 6,
    "m9anx": 9,
    "xsNerox": 2,
    "RiseCPvP": 4,
    "dylan20392334": 1,
    ".Fofolowwy": 1
  },
  "kitStats": {
    "build": 5,
    "survival": 9,
    "pvp": 15,
    "dupe": 5,
    "tools": 10,
    "stash": 2,
    "raid": 3,
    "wood": 8,
    "exp": 1,
    "dye": 2,
    "wool": 3,
    "mineral": 2,
    "food": 3,
    "redstone": 1
  }
}