{
  "serverIp": "8b8t.me",
  "lastUpdated": "21:06:33 25/1/2026",
  "totalKits": 0,
  "todayKits": 0,
  "onlineCount": 29,
  "peakPlayers": 29,
  "tps": "1.0",
  "ping": 0,
  "topUsers": [
    {
      "name": "Hien2309",
      "count": 1
    }
  ],
  "topKits": [
    {
      "name": "stash",
      "count": 1
    }
  ],
  "chatLog": [
    "[14:02] [8b8t] >> Welcome 0_HienBot to 8b8t.me Lobby",
    "[14:02] [8b8t] >> Welcome iTrisstan to 8b8t.me Lobby",
    "[14:02] <0_HienBot> >Hate those who destroy Hien2309's base",
    "[14:02] [8b8t] Unknown command do /help",
    "[14:02] You are already trying to connect to a server!",
    "[14:02] [8b8t] >> You can vote for [8b8t] at https://votefor.8b8t.me",
    "[14:02] You are already connected to this server!",
    "[14:02] [8b8t] >> You have killed yourself!",
    "[14:02] [Pro] <⛩ᏗᏒᏁᎧ⛏> > test ⏐ ʳᵘˢʰᵉʳʰᵃᶜᵏ ",
    "[14:02] [BOT] <0_HienBot> >In its beginnings 8b8t was actually called 0b0t ",
    "[14:03] [8b8t] >> Visit https://votefor.8b8t.me and vote to receive 2 additional render distance, 5 extra homes and access to the donkey dupe for free",
    "[14:03] [BOT] <0_HienBot> >Use !ʟᴀɴɢ and select your language ",
    "[14:04] [BOT] <0_HienBot> >Hate those who destroy Hien2309's base ",
    "[14:04] [BOT] <0_HienBot> >Want to see whose ping is the best? Chat !ʙᴇsᴛᴘɪɴɢ ",
    "[14:04] [8b8t] >> Join the official announcement discord server at https://discord.8b8t.me",
    "[14:05] \n \n \n \n \n \n \n \n \n \n \n \n \n \n \n \n \n \n \n \n \n \n \n \n \n \n \n \n \n \n ",
    "[14:05] [8b8t] >> Your login session has been continued.",
    "[14:05] [8b8t] >> Welcome 0_HienBot to 8b8t.me Lobby",
    "[14:06] [8b8t] Unknown command do /help",
    "[14:06] [8b8t] Unknown command do /help",
    "[14:06] ",
    "[14:06]  [8builders8tools]",
    "[14:06]  Perform the command /discord add to register",
    "[14:06]  your discord. By doing so, you",
    "[14:06]  decrease the chance of being hacked.",
    "[14:06] ",
    "[14:06]   [Confirm read]",
    "[14:06] ",
    "[14:06] [8b8t] >> You can vote for [8b8t] at https://votefor.8b8t.me",
    "[14:06] You are already connected to this server!"
  ],
  "userStats": {
    "Hien2309": 1
  },
  "kitStats": {
    "stash": 1
  }
}