{
  "serverIp": "8b8t.me",
  "lastUpdated": "04:18:28 26/1/2026",
  "totalKits": 271,
  "todayKits": 186,
  "onlineCount": 31,
  "peakPlayers": 51,
  "tps": "7.0",
  "ping": 211,
  "topUsers": [
    {
      "name": "rezhuhohlov",
      "count": 192
    },
    {
      "name": ".Maddie8171111",
      "count": 24
    },
    {
      "name": "Maverick0624",
      "count": 22
    },
    {
      "name": "Kidpoison",
      "count": 20
    },
    {
      "name": ".oneonefour14",
      "count": 19
    },
    {
      "name": "EvenMariotime",
      "count": 16
    },
    {
      "name": "Ayden322",
      "count": 15
    },
    {
      "name": "worldsaverizzler",
      "count": 15
    },
    {
      "name": "DORITOS_H",
      "count": 10
    },
    {
      "name": "LyoxYT",
      "count": 9
    }
  ],
  "topKits": [
    {
      "name": "pvp",
      "count": 144
    },
    {
      "name": "armortrims",
      "count": 72
    },
    {
      "name": "survival",
      "count": 43
    },
    {
      "name": "dupe",
      "count": 30
    },
    {
      "name": "elytra",
      "count": 29
    }
  ],
  "chatLog": [
    "[21:16] .MRPP21097 has made the advancement [Minecraft: Trial(s) Edition]",
    "[21:16] rezhuhohlov Whispers: !kit Elytra",
    "[21:16] [8b8t] >> Teleporting to home 0...",
    "[21:16] [8b8t] >> Teleporting to home 6...",
    "[21:16] To rezhuhohlov: Your kit (Elytra) will be delivered in 30 seconds! Dont forget to join dsc.gg/hienbot",
    "[21:16] To rezhuhohlov: Please chat \"/tpayes 0_HienBot\" within 35 seconds! Join dsc.gg/hienbot for updates.",
    "[21:16] [8b8t] >> Request sent to rezhuhohlov",
    "[21:16] [BOT] <0_HienBot> >Hmmmmmmmmm ",
    "[21:17] rezhuhohlov Whispers: !kit Elytra",
    "[21:17] To rezhuhohlov: Please wait a moment. Dont forget to join HienBot Group dsc.gg/hienbot",
    "[21:17] [8b8t] >> Teleporting...",
    "[21:17] [BOT] <0_HienBot> >In its beginnings 8b8t was actually called 0b0t ",
    "[21:17] [8b8t] >> You have killed yourself!",
    "[21:17] rezhuhohlov Whispers: !kit Elytra",
    "[21:17] To rezhuhohlov: You're on cooldown, try again in 15 seconds! Dont forget to join dsc.gg/hienbot",
    "[21:17] rezhuhohlov Whispers: !kit Elytra",
    "[21:17] [8b8t] >> Teleporting to home 0...",
    "[21:17] [8b8t] >> Teleporting to home 6...",
    "[21:17] To rezhuhohlov: Your kit (Elytra) will be delivered in 30 seconds! Dont forget to join dsc.gg/hienbot",
    "[21:17] To rezhuhohlov: Please chat \"/tpayes 0_HienBot\" within 35 seconds! Join dsc.gg/hienbot for updates.",
    "[21:17] [BOT] <0_HienBot> >Do you want kit? Type *кιт ",
    "[21:17] [8b8t] >> Request sent to rezhuhohlov",
    "[21:18] [8b8t] >> Join the official announcement discord server at https://discord.8b8t.me",
    "[21:18] rezhuhohlov Whispers: !kit Elytra",
    "[21:18] To rezhuhohlov: Please wait a moment. Dont forget to join HienBot Group dsc.gg/hienbot",
    "[21:18] [8b8t] >> The TPA request you sent to rezhuhohlov has expired.",
    "[21:18] rezhuhohlov Whispers: !kit Elytra",
    "[21:18] To rezhuhohlov: Please wait a moment. Dont forget to join HienBot Group dsc.gg/hienbot",
    "[21:18] <VientMC> quien tiene mapas porno?? ",
    "[21:18] [BOT] <0_HienBot> >Hate those who destroy Hien2309's base "
  ],
  "userStats": {
    "Hien2309": 1,
    "doyoda1292": 4,
    ".monolithpm": 1,
    "ItsMeMario_XD": 6,
    "LyoxYT": 9,
    "ReljKo7": 3,
    "botchaosonix666": 5,
    "Ayden322": 15,
    ".Maddie8171111": 24,
    "CHRastyyy": 4,
    "VientMC": 3,
    "liviaaaaaaa": 7,
    ".wietyy": 2,
    "Murad2002": 4,
    "AdustCloud3179": 2,
    "dylans117877601": 3,
    "Nighten2": 3,
    "BdubH2015": 9,
    "rezhuhohlov": 192,
    "Maverick0624": 22,
    "Hugoyouh": 3,
    "Kidpoison": 20,
    "bananastik": 2,
    "setelezsx": 2,
    "DORITOS_H": 10,
    "guserghi": 1,
    "Xx_COCACOLA_xX": 4,
    "YourWorstN8tmr": 3,
    "AstralAurora": 2,
    "JunkBass3801105": 6,
    "D4RK_K1NG": 1,
    "worldsaverizzler": 15,
    "SUS3106": 8,
    "jtorpey3": 8,
    "MrBeax31": 1,
    "EvenMariotime": 16,
    ".oneonefour14": 19,
    "MAKU_PRO_002": 2,
    "FlameeX3": 1,
    "albertkiller2008": 1,
    "abdlhmt": 4,
    "Richator3000": 7,
    ".XBLAZEFOOTX": 1,
    "ALSIO1243": 1
  },
  "kitStats": {
    "stash": 15,
    "pvp": 144,
    "build": 7,
    "dupe": 30,
    "survival": 43,
    "elytra": 29,
    "exp": 1,
    "shulker": 9,
    "redstone": 10,
    "lightsources": 4,
    "gap": 4,
    "wood": 11,
    "gterracotta": 4,
    "armortrims": 72,
    "food": 3,
    "toolbox": 3,
    "raid": 10,
    "terracotta": 2,
    "tools": 21,
    "quartz": 3,
    "wool": 3,
    "glass": 3,
    "mineral": 11,
    "highway": 3,
    "music": 2,
    "end": 3,
    "concrete": 4,
    "dye": 2,
    "ocean": 1
  }
}